LICENSE
MANIFEST.in
README.md
auth-token.service
install.sh
setup.py
avvyas_csr_azure_utils.egg-info/PKG-INFO
avvyas_csr_azure_utils.egg-info/SOURCES.txt
avvyas_csr_azure_utils.egg-info/dependency_links.txt
avvyas_csr_azure_utils.egg-info/requires.txt
avvyas_csr_azure_utils.egg-info/top_level.txt
csr_cloud/__init__.py
csr_cloud/aad_auth.py
csr_cloud/as_azure.py
csr_cloud/auth_mgr.py
csr_cloud/azure_utils.py
csr_cloud/blob_utils.py
csr_cloud/clear_aad_application_list.py
csr_cloud/clear_default_aad_app.py
csr_cloud/clear_token.py
csr_cloud/csr_cloud.py
csr_cloud/eventhub_utils.py
csr_cloud/file_utils.py
csr_cloud/general_utils.py
csr_cloud/ha_azure.py
csr_cloud/meta_utils.py
csr_cloud/metric_utils.py
csr_cloud/msi_auth.py
csr_cloud/refresh_token.py
csr_cloud/servicebus_utils.py
csr_cloud/set_default_aad_app.py
csr_cloud/show_auth_applications.py
csr_cloud/token_api.py
csr_cloud/token_svr.py