Metadata-Version: 2.1
Name: avvyas-csr-azure-utils
Version: 2.0.8
Summary: Utilities for csr1000v on Azure
Home-page: https://github4-chn.cisco.com/csr1000v-azure/avvyas-csr_azure_utils
Author: Cisco Systems Inc.
Author-email: csr-cloud-dev@cisco.com
License: MIT
Download-URL: https://github4-chn.cisco.com/csr1000v-azure/avvyas-csr_azure_utils/archive/2.0.8.tar.gz
Keywords: cisco,azure,guestshell,csr1000v
Platform: UNKNOWN
Classifier: Development Status :: 3 - Alpha
Classifier: Intended Audience :: Developers
Classifier: License :: OSI Approved :: MIT License
Classifier: Programming Language :: Python :: 2.7
Classifier: Programming Language :: Python :: 3.6
License-File: LICENSE
